<node type="RIL_TEXTLINE" X="66" Y="744" W="40" H="48" angle="0.000000000">
    <node type="RIL_WORD" X="66" Y="744" W="40" H="48">о</node>
</node>
<node type="RIL_TEXTLINE" X="40" Y="744" W="40" H="48" angle="-0.000000000">
    <node type="RIL_WORD" X="40" Y="744" W="40" H="48">о</node>
</node>
<node type="RIL_TEXTLINE" X="42" Y="398" W="42" H="38" angle="0.000000000">
    <node type="RIL_WORD" X="42" Y="398" W="42" H="38">о</node>
</node>
<node type="RIL_TEXTLINE" X="42" Y="352" W="42" H="50" angle="-0.000000000">
    <node type="RIL_WORD" X="42" Y="352" W="42" H="50">о</node>
</node>
<node type="RIL_TEXTLINE" X="42" Y="152" W="42" H="38" angle="-0.000000000">
    <node type="RIL_WORD" X="42" Y="152" W="42" H="38">1о</node>
</node>
<node type="RIL_TEXTLINE" X="40" Y="788" W="62" H="42" angle="-0.000000000">
    <node type="RIL_WORD" X="40" Y="788" W="62" H="42">о</node>
</node>
<node type="RIL_TEXTLINE" X="104" Y="972" W="86" H="44" angle="0.000000000">
    <node type="RIL_WORD" X="104" Y="972" W="86" H="44">нах</node>
</node>
<node type="RIL_TEXTLINE" X="38" Y="978" W="94" H="56" angle="-0.000000000">
    <node type="RIL_WORD" X="38" Y="978" W="94" H="56">е</node>
</node>
<node type="RIL_TEXTLINE" X="118" Y="318" W="576" H="46" angle="-0.000000000">
    <node type="RIL_WORD" X="118" Y="318" W="115" H="46">жупликов</node>
    <node type="RIL_WORD" X="246" Y="318" W="44" H="46">дляе</node>
    <node type="RIL_WORD" X="303" Y="318" W="153" H="46">передаочение,</node>
    <node type="RIL_WORD" X="470" Y="318" W="12" H="46">а</node>
    <node type="RIL_WORD" X="495" Y="318" W="76" H="46">такте</node>
    <node type="RIL_WORD" X="585" Y="318" W="108" H="46">ворочнок,</node>
</node>
<node type="RIL_TEXTLINE" X="176" Y="44" W="612" H="42" angle="-0.000000000">
    <node type="RIL_WORD" X="176" Y="44" W="170" H="42">Бакпериольная</node>
    <node type="RIL_WORD" X="364" Y="44" W="82" H="42">клетка</node>
    <node type="RIL_WORD" X="464" Y="44" W="82" H="42">обечно</node>
    <node type="RIL_WORD" X="564" Y="44" W="117" H="42">успроена</node>
    <node type="RIL_WORD" X="693" Y="44" W="94" H="42">набыле</node>
</node>
<node type="RIL_TEXTLINE" X="130" Y="588" W="614" H="44" angle="0.643745422">
    <node type="RIL_WORD" X="130" Y="588" W="177" H="44">пентидамкан</node>
    <node type="RIL_WORD" X="326" Y="588" W="25" H="44">По</node>
    <node type="RIL_WORD" X="364" Y="588" W="139" H="44">кмичекацу</node>
    <node type="RIL_WORD" X="516" Y="588" W="82" H="44">состпову</node>
    <node type="RIL_WORD" X="617" Y="588" W="126" H="44">клерочные</node>
</node>
<node type="RIL_TEXTLINE" X="126" Y="638" W="616" H="46" angle="-0.000000000">
    <node type="RIL_WORD" X="126" Y="638" W="112" H="46">метраны</node>
    <node type="RIL_WORD" X="258" Y="638" W="105" H="46">бктерй</node>
    <node type="RIL_WORD" X="377" Y="638" W="86" H="46">гораздо</node>
    <node type="RIL_WORD" X="477" Y="638" W="165" H="46">разнообразее</node>
    <node type="RIL_WORD" X="662" Y="638" W="79" H="46">мелбтан</node>
</node>
<node type="RIL_TEXTLINE" X="118" Y="798" W="628" H="46" angle="-0.000000000">
    <node type="RIL_WORD" X="118" Y="798" W="104" H="46">испотиве</node>
    <node type="RIL_WORD" X="235" Y="798" W="85" H="46">служаев,</node>
    <node type="RIL_WORD" X="333" Y="798" W="71" H="46">какт-</node>
    <node type="RIL_WORD" X="418" Y="798" W="39" H="46">лобо</node>
    <node type="RIL_WORD" X="471" Y="798" W="150" H="46">леабранных</node>
    <node type="RIL_WORD" X="634" Y="798" W="111" H="46">органемм</node>
</node>
<node type="RIL_TEXTLINE" X="172" Y="424" W="628" H="46" angle="-0.314808816">
    <node type="RIL_WORD" X="172" Y="424" W="39" H="46">Дся</node>
    <node type="RIL_WORD" X="231" Y="424" W="99" H="46">волведение</node>
    <node type="RIL_WORD" X="343" Y="424" W="92" H="46">восеств</node>
    <node type="RIL_WORD" X="449" Y="424" W="6" H="46">в</node>
    <node type="RIL_WORD" X="476" Y="424" W="46" H="46">поа</node>
    <node type="RIL_WORD" X="535" Y="424" W="59" H="46">четле</node>
    <node type="RIL_WORD" X="608" Y="424" W="105" H="46">факторов</node>
    <node type="RIL_WORD" X="727" Y="424" W="72" H="46">пато-</node>
</node>
<node type="RIL_TEXTLINE" X="128" Y="204" W="628" H="48" angle="-0.000000000">
    <node type="RIL_WORD" X="128" Y="204" W="101" H="48">которая</node>
    <node type="RIL_WORD" X="242" Y="204" W="87" H="48">сзужити</node>
    <node type="RIL_WORD" X="344" Y="204" W="114" H="48">зачитной</node>
    <node type="RIL_WORD" X="479" Y="204" W="33" H="48">от</node>
    <node type="RIL_WORD" X="533" Y="204" W="94" H="48">вленней</node>
    <node type="RIL_WORD" X="641" Y="204" W="60" H="48">сроды,</node>
    <node type="RIL_WORD" X="715" Y="204" W="40" H="48">жся</node>
</node>
<node type="RIL_TEXTLINE" X="124" Y="850" W="634" H="48" angle="-0.000000000">
    <node type="RIL_WORD" X="124" Y="850" W="74" H="48">Викте</node>
    <node type="RIL_WORD" X="218" Y="850" W="6" H="48">с</node>
    <node type="RIL_WORD" X="238" Y="850" W="53" H="48">теи</node>
    <node type="RIL_WORD" X="306" Y="850" W="6" H="48">у</node>
    <node type="RIL_WORD" X="326" Y="850" W="53" H="48">ряда</node>
    <node type="RIL_WORD" X="387" Y="850" W="107" H="48">бактерй</node>
    <node type="RIL_WORD" X="508" Y="850" W="101" H="48">лавотся</node>
    <node type="RIL_WORD" X="629" Y="850" W="128" H="48">клопочные</node>
</node>
<node type="RIL_TEXTLINE" X="128" Y="530" W="648" H="46" angle="-0.000000000">
    <node type="RIL_WORD" X="128" Y="530" W="105" H="46">секреми</node>
    <node type="RIL_WORD" X="247" Y="530" W="132" H="46">Тлепочная</node>
    <node type="RIL_WORD" X="392" Y="530" W="79" H="46">отенка</node>
    <node type="RIL_WORD" X="485" Y="530" W="105" H="46">бактоий</node>
    <node type="RIL_WORD" X="604" Y="530" W="72" H="46">абкно</node>
    <node type="RIL_WORD" X="690" Y="530" W="85" H="46">сдерост</node>
</node>
<node type="RIL_TEXTLINE" X="124" Y="262" W="656" H="46" angle="0.000000000">
    <node type="RIL_WORD" X="124" Y="262" W="83" H="46">лночо</node>
    <node type="RIL_WORD" X="220" Y="262" W="192" H="46">свободнатноврлено</node>
    <node type="RIL_WORD" X="419" Y="262" W="109" H="46">бактерй</node>
    <node type="RIL_WORD" X="542" Y="262" W="135" H="46">характерьно</node>
    <node type="RIL_WORD" X="689" Y="262" W="90" H="46">налкие</node>
</node>
<node type="RIL_TEXTLINE" X="120" Y="476" W="660" H="50" angle="-0.481465816">
    <node type="RIL_WORD" X="120" Y="476" W="118" H="50">генностицз</node>
    <node type="RIL_WORD" X="252" Y="476" W="6" H="50">в</node>
    <node type="RIL_WORD" X="272" Y="476" W="159" H="50">окружаюащю</node>
    <node type="RIL_WORD" X="446" Y="476" W="62" H="50">Феу</node>
    <node type="RIL_WORD" X="516" Y="476" W="166" H="50">испаеются</node>
    <node type="RIL_WORD" X="696" Y="476" W="83" H="50">сючеся</node>
</node>
<node type="RIL_TEXTLINE" X="126" Y="906" W="662" H="52" angle="-0.241752908">
    <node type="RIL_WORD" X="126" Y="906" W="154" H="52">опруктурые,</node>
    <node type="RIL_WORD" X="287" Y="906" W="29" H="52">не</node>
    <node type="RIL_WORD" X="331" Y="906" W="95" H="52">шнасне</node>
    <node type="RIL_WORD" X="442" Y="906" W="102" H="52">аналогов</node>
    <node type="RIL_WORD" X="559" Y="906" W="7" H="52">в</node>
    <node type="RIL_WORD" X="582" Y="906" W="44" H="52">двух</node>
    <node type="RIL_WORD" X="640" Y="906" W="73" H="52">други</node>
    <node type="RIL_WORD" X="729" Y="906" W="58" H="52">доле-</node>
</node>
<node type="RIL_TEXTLINE" X="122" Y="150" W="664" H="48" angle="0.487609863">
    <node type="RIL_WORD" X="122" Y="150" W="41" H="48">мов.</node>
    <node type="RIL_WORD" X="176" Y="150" W="171" H="48">Бакмериальные</node>
    <node type="RIL_WORD" X="368" Y="150" W="88" H="48">клетки</node>
    <node type="RIL_WORD" X="471" Y="150" W="61" H="48">чато</node>
    <node type="RIL_WORD" X="553" Y="150" W="116" H="48">окружает</node>
    <node type="RIL_WORD" X="690" Y="150" W="95" H="48">канерма,</node>
</node>
<node type="RIL_TEXTLINE" X="122" Y="746" W="666" H="50" angle="-0.776844323">
    <node type="RIL_WORD" X="122" Y="746" W="48" H="50">ры</node>
    <node type="RIL_WORD" X="176" Y="746" W="27" H="50">не</node>
    <node type="RIL_WORD" X="218" Y="746" W="82" H="50">шент</node>
    <node type="RIL_WORD" X="314" Y="746" W="178" H="50">огранинченного</node>
    <node type="RIL_WORD" X="499" Y="746" W="102" H="50">обтлаской</node>
    <node type="RIL_WORD" X="616" Y="746" W="48" H="50">дра</node>
    <node type="RIL_WORD" X="678" Y="746" W="13" H="50">ц</node>
    <node type="RIL_WORD" X="705" Y="746" W="13" H="50">в</node>
    <node type="RIL_WORD" X="733" Y="746" W="54" H="50">былс-</node>
</node>
<node type="RIL_TEXTLINE" X="122" Y="690" W="674" H="52" angle="-0.469627023">
    <node type="RIL_WORD" X="122" Y="690" W="193" H="52">зукариютических</node>
    <node type="RIL_WORD" X="337" Y="690" W="78" H="52">кетий</node>
    <node type="RIL_WORD" X="437" Y="690" W="7" H="52">в</node>
    <node type="RIL_WORD" X="458" Y="690" W="93" H="52">опмче</node>
    <node type="RIL_WORD" X="566" Y="690" W="28" H="52">ом</node>
    <node type="RIL_WORD" X="609" Y="690" W="114" H="52">дукареоми</node>
    <node type="RIL_WORD" X="738" Y="690" W="57" H="52">басле</node>
</node>
<node type="RIL_TEXTLINE" X="118" Y="96" W="682" H="46" angle="-0.000000000">
    <node type="RIL_WORD" X="118" Y="96" W="77" H="46">просто</node>
    <node type="RIL_WORD" X="214" Y="96" W="25" H="46">по</node>
    <node type="RIL_WORD" X="253" Y="96" W="122" H="46">дравлено</node>
    <node type="RIL_WORD" X="381" Y="96" W="12" H="46">с</node>
    <node type="RIL_WORD" X="407" Y="96" W="122" H="46">клетками</node>
    <node type="RIL_WORD" X="542" Y="96" W="70" H="46">дуио</node>
    <node type="RIL_WORD" X="626" Y="96" W="64" H="46">твх</node>
    <node type="RIL_WORD" X="703" Y="96" W="96" H="46">дганиц-</node>
</node>
<node type="RIL_TABLE">
    <node type="RIL_CELL" x="440" y="507" w="82" h="211"></node>
    <node type="RIL_CELL" x="389" y="507" w="52" h="54"></node>
    <node type="RIL_CELL" x="467" y="318" w="56" h="163"></node>
    <node type="RIL_CELL" x="38" y="508" w="108" h="27"></node>
    <node type="RIL_CELL" x="309" y="747" w="107" h="211"></node>
    <node type="RIL_CELL" x="658" y="588" w="107" h="107"></node>
    <node type="RIL_CELL" x="148" y="589" w="54" h="53"></node>
    <node type="RIL_CELL" x="231" y="13" w="45" h="167"></node>
    <node type="RIL_CELL" x="249" y="13" w="27" h="59"></node>
    <node type="RIL_CELL" x="270" y="14" w="35" h="29"></node>
    <node type="RIL_CELL" x="305" y="14" w="8" h="37"></node>
    <node type="RIL_CELL" x="313" y="14" w="20" h="31"></node>
    <node type="RIL_CELL" x="333" y="14" w="27" h="31"></node>
    <node type="RIL_CELL" x="360" y="14" w="28" h="31"></node>
    <node type="RIL_CELL" x="388" y="14" w="27" h="30"></node>
    <node type="RIL_CELL" x="415" y="13" w="109" h="111"></node>
    <node type="RIL_CELL" x="606" y="13" w="28" h="110"></node>
    <node type="RIL_CELL" x="633" y="13" w="47" h="110"></node>
    <node type="RIL_CELL" x="631" y="13" w="139" h="467"></node>
    <node type="RIL_CELL" x="765" y="13" w="43" h="575"></node>
    <node type="RIL_CELL" x="249" y="13" w="56" h="59"></node>
    <node type="RIL_CELL" x="305" y="45" w="28" h="27"></node>
    <node type="RIL_CELL" x="334" y="45" w="27" h="27"></node>
    <node type="RIL_CELL" x="361" y="44" w="27" h="27"></node>
    <node type="RIL_CELL" x="388" y="44" w="27" h="22"></node>
    <node type="RIL_CELL" x="415" y="44" w="68" h="28"></node>
    <node type="RIL_CELL" x="276" y="71" w="30" h="26"></node>
    <node type="RIL_CELL" x="385" y="66" w="31" h="113"></node>
    <node type="RIL_CELL" x="305" y="71" w="28" h="52"></node>
    <node type="RIL_CELL" x="334" y="71" w="27" h="28"></node>
    <node type="RIL_CELL" x="334" y="71" w="54" h="82"></node>
    <node type="RIL_CELL" x="415" y="72" w="27" h="27"></node>
    <node type="RIL_CELL" x="442" y="71" w="38" h="28"></node>
    <node type="RIL_CELL" x="397" y="72" w="18" h="54"></node>
    <node type="RIL_CELL" x="274" y="97" w="17" h="24"></node>
    <node type="RIL_CELL" x="291" y="97" w="15" h="23"></node>
    <node type="RIL_CELL" x="334" y="99" w="44" h="24"></node>
    <node type="RIL_CELL" x="415" y="99" w="27" h="27"></node>
    <node type="RIL_CELL" x="442" y="99" w="28" h="27"></node>
    <node type="RIL_CELL" x="277" y="120" w="29" h="33"></node>
    <node type="RIL_CELL" x="306" y="120" w="28" h="33"></node>
    <node type="RIL_CELL" x="469" y="124" w="55" h="194"></node>
    <node type="RIL_CELL" x="523" y="13" w="163" h="304"></node>
    <node type="RIL_CELL" x="404" y="126" w="11" h="27"></node>
    <node type="RIL_CELL" x="415" y="126" w="27" h="27"></node>
    <node type="RIL_CELL" x="442" y="125" w="28" h="28"></node>
    <node type="RIL_CELL" x="470" y="125" w="27" h="83"></node>
    <node type="RIL_CELL" x="277" y="154" w="29" h="24"></node>
    <node type="RIL_CELL" x="307" y="154" w="27" h="26"></node>
    <node type="RIL_CELL" x="334" y="153" w="54" h="27"></node>
    <node type="RIL_CELL" x="415" y="153" w="27" h="55"></node>
    <node type="RIL_CELL" x="442" y="153" w="28" h="55"></node>
    <node type="RIL_CELL" x="247" y="175" w="32" h="35"></node>
    <node type="RIL_CELL" x="278" y="178" w="29" h="30"></node>
    <node type="RIL_CELL" x="307" y="178" w="27" h="30"></node>
    <node type="RIL_CELL" x="236" y="175" w="15" h="23"></node>
    <node type="RIL_CELL" x="334" y="180" w="27" h="28"></node>
    <node type="RIL_CELL" x="361" y="180" w="27" h="28"></node>
    <node type="RIL_CELL" x="388" y="180" w="27" h="28"></node>
    <node type="RIL_CELL" x="210" y="197" w="42" h="103"></node>
    <node type="RIL_CELL" x="233" y="208" w="46" h="43"></node>
    <node type="RIL_CELL" x="279" y="208" w="27" h="27"></node>
    <node type="RIL_CELL" x="307" y="208" w="27" h="28"></node>
    <node type="RIL_CELL" x="334" y="208" w="27" h="28"></node>
    <node type="RIL_CELL" x="361" y="208" w="55" h="28"></node>
    <node type="RIL_CELL" x="415" y="208" w="27" h="28"></node>
    <node type="RIL_CELL" x="443" y="208" w="27" h="27"></node>
    <node type="RIL_CELL" x="470" y="208" w="27" h="27"></node>
    <node type="RIL_CELL" x="251" y="235" w="28" h="31"></node>
    <node type="RIL_CELL" x="280" y="235" w="27" h="28"></node>
    <node type="RIL_CELL" x="307" y="235" w="27" h="28"></node>
    <node type="RIL_CELL" x="415" y="236" w="27" h="27"></node>
    <node type="RIL_CELL" x="442" y="235" w="28" h="28"></node>
    <node type="RIL_CELL" x="334" y="236" w="32" h="27"></node>
    <node type="RIL_CELL" x="361" y="236" w="27" h="27"></node>
    <node type="RIL_CELL" x="388" y="236" w="27" h="27"></node>
    <node type="RIL_CELL" x="244" y="264" w="7" h="15"></node>
    <node type="RIL_CELL" x="251" y="263" w="28" h="25"></node>
    <node type="RIL_CELL" x="280" y="263" w="27" h="26"></node>
    <node type="RIL_CELL" x="307" y="263" w="26" h="28"></node>
    <node type="RIL_CELL" x="334" y="263" w="32" h="28"></node>
    <node type="RIL_CELL" x="361" y="263" w="27" h="55"></node>
    <node type="RIL_CELL" x="388" y="263" w="27" h="55"></node>
    <node type="RIL_CELL" x="416" y="263" w="26" h="27"></node>
    <node type="RIL_CELL" x="442" y="263" w="27" h="27"></node>
    <node type="RIL_CELL" x="244" y="279" w="8" h="8"></node>
    <node type="RIL_CELL" x="224" y="288" w="19" h="12"></node>
    <node type="RIL_CELL" x="244" y="288" w="8" h="13"></node>
    <node type="RIL_CELL" x="252" y="288" w="29" h="57"></node>
    <node type="RIL_CELL" x="280" y="289" w="27" h="29"></node>
    <node type="RIL_CELL" x="307" y="289" w="27" h="29"></node>
    <node type="RIL_CELL" x="415" y="290" w="27" h="28"></node>
    <node type="RIL_CELL" x="442" y="290" w="27" h="28"></node>
    <node type="RIL_CELL" x="334" y="291" w="27" h="27"></node>
    <node type="RIL_CELL" x="361" y="291" w="27" h="53"></node>
    <node type="RIL_CELL" x="160" y="300" w="65" h="73"></node>
    <node type="RIL_CELL" x="224" y="300" w="13" h="24"></node>
    <node type="RIL_CELL" x="237" y="300" w="6" h="16"></node>
    <node type="RIL_CELL" x="244" y="300" w="8" h="16"></node>
    <node type="RIL_CELL" x="202" y="320" w="22" h="33"></node>
    <node type="RIL_CELL" x="237" y="316" w="6" h="8"></node>
    <node type="RIL_CELL" x="242" y="316" w="9" h="9"></node>
    <node type="RIL_CELL" x="280" y="318" w="28" h="27"></node>
    <node type="RIL_CELL" x="307" y="318" w="27" h="27"></node>
    <node type="RIL_CELL" x="334" y="318" w="27" h="27"></node>
    <node type="RIL_CELL" x="388" y="318" w="27" h="27"></node>
    <node type="RIL_CELL" x="415" y="318" w="27" h="110"></node>
    <node type="RIL_CELL" x="441" y="318" w="81" h="189"></node>
    <node type="RIL_CELL" x="202" y="320" w="35" h="33"></node>
    <node type="RIL_CELL" x="237" y="325" w="5" h="9"></node>
    <node type="RIL_CELL" x="209" y="324" w="44" h="29"></node>
    <node type="RIL_CELL" x="209" y="345" w="44" h="28"></node>
    <node type="RIL_CELL" x="335" y="344" w="27" h="29"></node>
    <node type="RIL_CELL" x="361" y="344" w="28" h="30"></node>
    <node type="RIL_CELL" x="389" y="344" w="26" h="84"></node>
    <node type="RIL_CELL" x="254" y="345" w="27" h="28"></node>
    <node type="RIL_CELL" x="281" y="345" w="27" h="29"></node>
    <node type="RIL_CELL" x="308" y="345" w="27" h="28"></node>
    <node type="RIL_CELL" x="136" y="370" w="37" h="88"></node>
    <node type="RIL_CELL" x="30" y="374" w="22" h="18"></node>
    <node type="RIL_CELL" x="172" y="373" w="27" h="27"></node>
    <node type="RIL_CELL" x="226" y="373" w="27" h="28"></node>
    <node type="RIL_CELL" x="254" y="373" w="28" h="28"></node>
    <node type="RIL_CELL" x="603" y="372" w="55" h="216"></node>
    <node type="RIL_CELL" x="281" y="373" w="27" h="28"></node>
    <node type="RIL_CELL" x="308" y="374" w="27" h="27"></node>
    <node type="RIL_CELL" x="335" y="374" w="27" h="27"></node>
    <node type="RIL_CELL" x="362" y="374" w="27" h="27"></node>
    <node type="RIL_CELL" x="5" y="377" w="24" h="15"></node>
    <node type="RIL_CELL" x="389" y="374" w="18" h="27"></node>
    <node type="RIL_CELL" x="5" y="392" w="25" h="35"></node>
    <node type="RIL_CELL" x="5" y="392" w="47" h="116"></node>
    <node type="RIL_CELL" x="173" y="400" w="27" h="27"></node>
    <node type="RIL_CELL" x="199" y="400" w="28" h="27"></node>
    <node type="RIL_CELL" x="227" y="400" w="27" h="27"></node>
    <node type="RIL_CELL" x="254" y="401" w="28" h="27"></node>
    <node type="RIL_CELL" x="282" y="401" w="27" h="27"></node>
    <node type="RIL_CELL" x="308" y="401" w="27" h="27"></node>
    <node type="RIL_CELL" x="335" y="401" w="27" h="27"></node>
    <node type="RIL_CELL" x="362" y="401" w="27" h="27"></node>
    <node type="RIL_CELL" x="173" y="427" w="27" h="27"></node>
    <node type="RIL_CELL" x="631" y="426" w="81" h="113"></node>
    <node type="RIL_CELL" x="200" y="427" w="28" h="27"></node>
    <node type="RIL_CELL" x="228" y="427" w="27" h="27"></node>
    <node type="RIL_CELL" x="254" y="427" w="28" h="26"></node>
    <node type="RIL_CELL" x="282" y="428" w="27" h="15"></node>
    <node type="RIL_CELL" x="306" y="428" w="30" h="53"></node>
    <node type="RIL_CELL" x="335" y="428" w="27" h="53"></node>
    <node type="RIL_CELL" x="362" y="428" w="27" h="25"></node>
    <node type="RIL_CELL" x="389" y="428" w="26" h="25"></node>
    <node type="RIL_CELL" x="389" y="428" w="53" h="79"></node>
    <node type="RIL_CELL" x="282" y="443" w="26" h="10"></node>
    <node type="RIL_CELL" x="38" y="457" w="108" h="52"></node>
    <node type="RIL_CELL" x="145" y="454" w="28" h="27"></node>
    <node type="RIL_CELL" x="228" y="453" w="27" h="28"></node>
    <node type="RIL_CELL" x="255" y="453" w="27" h="28"></node>
    <node type="RIL_CELL" x="282" y="453" w="27" h="29"></node>
    <node type="RIL_CELL" x="362" y="453" w="27" h="54"></node>
    <node type="RIL_CELL" x="173" y="454" w="28" h="27"></node>
    <node type="RIL_CELL" x="200" y="454" w="28" h="27"></node>
    <node type="RIL_CELL" x="658" y="480" w="108" h="108"></node>
    <node type="RIL_CELL" x="174" y="481" w="27" h="26"></node>
    <node type="RIL_CELL" x="201" y="481" w="27" h="27"></node>
    <node type="RIL_CELL" x="229" y="481" w="27" h="27"></node>
    <node type="RIL_CELL" x="255" y="481" w="27" h="27"></node>
    <node type="RIL_CELL" x="282" y="481" w="27" h="27"></node>
    <node type="RIL_CELL" x="309" y="482" w="26" h="25"></node>
    <node type="RIL_CELL" x="336" y="482" w="26" h="25"></node>
    <node type="RIL_CELL" x="522" y="481" w="61" h="26"></node>
    <node type="RIL_CELL" x="146" y="507" w="28" h="28"></node>
    <node type="RIL_CELL" x="174" y="507" w="28" h="28"></node>
    <node type="RIL_CELL" x="310" y="507" w="26" h="28"></node>
    <node type="RIL_CELL" x="336" y="507" w="53" h="28"></node>
    <node type="RIL_CELL" x="201" y="508" w="28" h="52"></node>
    <node type="RIL_CELL" x="282" y="507" w="27" h="28"></node>
    <node type="RIL_CELL" x="522" y="507" w="27" h="241"></node>
    <node type="RIL_CELL" x="549" y="507" w="42" h="241"></node>
    <node type="RIL_CELL" x="4" y="508" w="229" h="573"></node>
    <node type="RIL_CELL" x="229" y="508" w="27" h="53"></node>
    <node type="RIL_CELL" x="256" y="508" w="26" h="27"></node>
    <node type="RIL_CELL" x="38" y="535" w="28" h="27"></node>
    <node type="RIL_CELL" x="65" y="535" w="27" h="27"></node>
    <node type="RIL_CELL" x="92" y="535" w="34" h="27"></node>
    <node type="RIL_CELL" x="120" y="535" w="27" h="27"></node>
    <node type="RIL_CELL" x="146" y="535" w="29" h="27"></node>
    <node type="RIL_CELL" x="175" y="535" w="27" h="25"></node>
    <node type="RIL_CELL" x="256" y="535" w="26" h="53"></node>
    <node type="RIL_CELL" x="282" y="535" w="33" h="78"></node>
    <node type="RIL_CELL" x="309" y="535" w="27" h="127"></node>
    <node type="RIL_CELL" x="336" y="535" w="53" h="127"></node>
    <node type="RIL_CELL" x="175" y="560" w="27" h="54"></node>
    <node type="RIL_CELL" x="202" y="560" w="27" h="28"></node>
    <node type="RIL_CELL" x="229" y="560" w="27" h="28"></node>
    <node type="RIL_CELL" x="147" y="560" w="28" h="53"></node>
    <node type="RIL_CELL" x="350" y="561" w="92" h="52"></node>
    <node type="RIL_CELL" x="66" y="562" w="27" h="27"></node>
    <node type="RIL_CELL" x="93" y="562" w="28" h="27"></node>
    <node type="RIL_CELL" x="120" y="562" w="27" h="27"></node>
    <node type="RIL_CELL" x="202" y="588" w="27" h="26"></node>
    <node type="RIL_CELL" x="229" y="588" w="27" h="26"></node>
    <node type="RIL_CELL" x="256" y="588" w="27" h="26"></node>
    <node type="RIL_CELL" x="603" y="588" w="55" h="54"></node>
    <node type="RIL_CELL" x="736" y="588" w="56" h="296"></node>
    <node type="RIL_CELL" x="93" y="589" w="55" h="80"></node>
    <node type="RIL_CELL" x="120" y="589" w="28" h="53"></node>
    <node type="RIL_CELL" x="357" y="611" w="32" h="53"></node>
    <node type="RIL_CELL" x="229" y="614" w="27" h="27"></node>
    <node type="RIL_CELL" x="256" y="613" w="27" h="81"></node>
    <node type="RIL_CELL" x="283" y="613" w="31" h="81"></node>
    <node type="RIL_CELL" x="442" y="612" w="62" h="135"></node>
    <node type="RIL_CELL" x="202" y="614" w="27" h="27"></node>
    <node type="RIL_CELL" x="202" y="641" w="27" h="20"></node>
    <node type="RIL_CELL" x="148" y="641" w="54" h="23"></node>
    <node type="RIL_CELL" x="578" y="642" w="25" h="53"></node>
    <node type="RIL_CELL" x="603" y="642" w="62" h="53"></node>
    <node type="RIL_CELL" x="202" y="662" w="27" h="6"></node>
    <node type="RIL_CELL" x="309" y="662" w="27" h="32"></node>
    <node type="RIL_CELL" x="336" y="662" w="80" h="57"></node>
    <node type="RIL_CELL" x="661" y="665" w="50" h="136"></node>
    <node type="RIL_CELL" x="257" y="694" w="26" h="26"></node>
    <node type="RIL_CELL" x="283" y="694" w="26" h="25"></node>
    <node type="RIL_CELL" x="309" y="694" w="26" h="26"></node>
    <node type="RIL_CELL" x="576" y="695" w="27" h="38"></node>
    <node type="RIL_CELL" x="603" y="695" w="80" h="65"></node>
    <node type="RIL_CELL" x="710" y="695" w="28" h="106"></node>
    <node type="RIL_CELL" x="737" y="695" w="27" h="106"></node>
    <node type="RIL_CELL" x="469" y="718" w="27" h="29"></node>
    <node type="RIL_CELL" x="496" y="718" w="26" h="29"></node>
    <node type="RIL_CELL" x="522" y="718" w="27" h="57"></node>
    <node type="RIL_CELL" x="229" y="719" w="187" h="362"></node>
    <node type="RIL_CELL" x="257" y="720" w="53" h="105"></node>
    <node type="RIL_CELL" x="283" y="720" w="26" h="27"></node>
    <node type="RIL_CELL" x="309" y="679" w="107" h="68"></node>
    <node type="RIL_CELL" x="416" y="747" w="26" h="211"></node>
    <node type="RIL_CELL" x="442" y="747" w="53" h="211"></node>
    <node type="RIL_CELL" x="469" y="747" w="27" h="53"></node>
    <node type="RIL_CELL" x="496" y="747" w="25" h="53"></node>
    <node type="RIL_CELL" x="549" y="748" w="27" h="14"></node>
    <node type="RIL_CELL" x="442" y="748" w="358" h="272"></node>
    <node type="RIL_CELL" x="469" y="800" w="27" h="76"></node>
    <node type="RIL_CELL" x="683" y="801" w="27" h="79"></node>
    <node type="RIL_CELL" x="709" y="801" w="27" h="75"></node>
    <node type="RIL_CELL" x="257" y="824" w="53" h="42"></node>
    <node type="RIL_CELL" x="5" y="362" w="25" h="15"></node>
    <node type="RIL_CELL" x="576" y="707" w="27" h="41"></node>
    <node type="RIL_CELL" x="657" y="599" w="54" h="67"></node>
</node>
